wg_meshconf/__init__.py
wg_meshconf/__main__.py
wg_meshconf/database_manager.py
wg_meshconf/wg_meshconf.py
wg_meshconf/wireguard.py
wg_meshconf-2.5.1.dist-info/entry_points.txt
wg_meshconf-2.5.1.dist-info/WHEEL
wg_meshconf-2.5.1.dist-info/METADATA
wg_meshconf-2.5.1.dist-info/licenses/LICENSE
wg_meshconf-2.5.1.dist-info/RECORD
