Metadata-Version: 2.1
Name: wg-meshconf
Version: 2.5.1
Summary: A tool that helps you to generate peer configuration files for WireGuard mesh networks
License: GPL-3.0-or-later
Author-email: K4YT3X <i@k4yt3x.com>
Requires-Python: >=3.7
Requires-Dist: cryptography>=35.0.0
Requires-Dist: rich>=12.0.0
Project-URL: homepage, https://github.com/k4yt3x/wg-meshconf
